restore_manager/__init__.py
restore_manager-0.1.0.dist-info/licenses/LICENSE
restore_manager-0.1.0.dist-info/licenses/LICENSE.GPL
restore_manager-0.1.0.dist-info/METADATA
restore_manager-0.1.0.dist-info/WHEEL
restore_manager-0.1.0.dist-info/entry_points.txt
restore_manager-0.1.0.dist-info/top_level.txt
restore_manager-0.1.0.dist-info/RECORD
