Metadata-Version: 2.4
Name: restore-manager
Version: 0.1.0
Summary: A command-line tool to snapshot and restore a folder's state.
Author-email: Your Name <your.email@example.com>
License: Please refer to the README.md for detailed licensing information. This project is dual-licensed under the GNU General Public License v3.0 (GPLv3) for open-source use and a commercial license for proprietary use. Contact [your.email@example.com] for commercial inquiries.
Project-URL: Homepage, https://github.com/brookcs3/restore-manager
Project-URL: Bug Tracker, https://github.com/brookcs3/restore-manager/issues
Keywords: backup,restore,snapshot,cli,filesystem
Classifier: Programming Language :: Python :: 3
Classifier: License :: OSI Approved :: MIT License
Classifier: Operating System :: MacOS :: MacOS X
Classifier: Operating System :: POSIX :: Linux
Classifier: Environment :: Console
Classifier: Intended Audience :: Developers
Classifier: Topic :: System :: Archiving :: Backup
Classifier: Topic :: Utilities
Requires-Python: >=3.8
License-File: LICENSE
License-File: LICENSE.GPL
Requires-Dist: xattr
Dynamic: license-file
